psytrack/__init__.py
psytrack/getMAP.py
psytrack/hyperOpt.py
psytrack/runSim.py
psytrack/examples/ExampleNotebook.ipynb
psytrack/examples/GraphicalAbstract.png
psytrack/examples/future_upgrades.txt
psytrack/examples/sampleRatData.npz
psytrack/examples/weights.png
psytrack/helper/__init__.py
psytrack/helper/crossValidation.py
psytrack/helper/helperFunctions.py
psytrack/helper/invBlkTriDiag.py
psytrack/helper/jacHessCheck.py
psytrack/helper/memoize.py
psytrack/plot/__init__.py
psytrack/plot/analysisFunctions.py
psytrack-2.0.2.dist-info/LICENSE
psytrack-2.0.2.dist-info/METADATA
psytrack-2.0.2.dist-info/WHEEL
psytrack-2.0.2.dist-info/top_level.txt
psytrack-2.0.2.dist-info/RECORD
