Metadata-Version: 2.2
Name: psytrack
Version: 2.0.2
Summary: Tool for tracking dynamic psychometric curves
Home-page: http://github.com/nicholas-roy/psytrack
Author: Nicholas A. Roy, Ji Hyun Bak, and Jonathan W. Pillow
Author-email: nicholas.roy.42@gmail.com
License: MIT
Classifier: Programming Language :: Python :: 3
Classifier: License :: OSI Approved :: MIT License
Classifier: Operating System :: OS Independent
Classifier: Intended Audience :: Science/Research
Classifier: Topic :: Scientific/Engineering
License-File: LICENSE
Requires-Dist: matplotlib
Requires-Dist: markdown
Requires-Dist: numpy
Requires-Dist: scipy
Dynamic: author
Dynamic: author-email
Dynamic: classifier
Dynamic: description
Dynamic: description-content-type
Dynamic: home-page
Dynamic: license
Dynamic: requires-dist
Dynamic: summary
